TkLogin/__init__.py
TkLogin/__main__.py
TkLogin/Data/Users_Database.json
TkLogin-0.0.4.dist-info/LICENSE
TkLogin-0.0.4.dist-info/METADATA
TkLogin-0.0.4.dist-info/WHEEL
TkLogin-0.0.4.dist-info/entry_points.txt
TkLogin-0.0.4.dist-info/top_level.txt
TkLogin-0.0.4.dist-info/RECORD
