Metadata-Version: 2.1
Name: TkLogin
Version: 0.0.4
Summary: Python Tkinter login
Home-page: https://github.com/carmelosammarco/TkLogin
Author: Carmelo Sammarco
Author-email: sammarcocarmelo@gmail.com
License: gpl-3.0
Platform: OS Independent
Classifier: Development Status :: 3 - Alpha
Classifier: Intended Audience :: Science/Research
Classifier: Topic :: Scientific/Engineering
Classifier: Programming Language :: Python :: 3.6
Requires-Python: >=3
Requires-Dist: ftputil (>=3.4)
